pandatask/__init__.py
pandatask/core.py
pandatask-0.0.1.dist-info/METADATA
pandatask-0.0.1.dist-info/WHEEL
pandatask-0.0.1.dist-info/top_level.txt
pandatask-0.0.1.dist-info/RECORD
