Metadata-Version: 2.1
Name: pandatask
Version: 0.0.1
Summary: 上传本地代码到服务端的工具
Home-page: UNKNOWN
Author: panda
Author-email: 915615059@qq.com
License: UNKNOWN
Platform: UNKNOWN
Requires-Dist: cloudpickle
Requires-Dist: requests
